mightstone/__init__.py
mightstone/app.py
mightstone/ass/__init__.py
mightstone/ass/compressor/__init__.py
mightstone/ass/compressor/async_file_obj.py
mightstone/ass/compressor/async_reader.py
mightstone/ass/compressor/async_writer.py
mightstone/ass/compressor/codecs/__init__.py
mightstone/ass/compressor/codecs/bzip2_codec.py
mightstone/ass/compressor/codecs/gzip_codec.py
mightstone/ass/compressor/codecs/lzma_codec.py
mightstone/ass/compressor/codecs/none_codec.py
mightstone/assets/LiberationMono-Regular.ttf
mightstone/assets/__init__.py
mightstone/cli/__init__.py
mightstone/cli/__main__.py
mightstone/cli/commands.py
mightstone/cli/models.py
mightstone/cli/utils.py
mightstone/common.py
mightstone/config.py
mightstone/container.py
mightstone/core.py
mightstone/hishel.py
mightstone/injector.py
mightstone/py.typed
mightstone/rule/__init__.py
mightstone/rule/data/__init__.py
mightstone/rule/data/abilities.json
mightstone/rule/data/ability.py
mightstone/rule/data/color.py
mightstone/rule/data/rules.json
mightstone/rule/data/rules.py
mightstone/rule/models/__init__.py
mightstone/rule/models/ability.py
mightstone/rule/models/color.py
mightstone/services/__init__.py
mightstone/services/cardconjurer/__init__.py
mightstone/services/cardconjurer/api.py
mightstone/services/cardconjurer/commands.py
mightstone/services/cardconjurer/models.py
mightstone/services/edhrec/__init__.py
mightstone/services/edhrec/api.py
mightstone/services/edhrec/commands.py
mightstone/services/edhrec/models.py
mightstone/services/mtgjson/__init__.py
mightstone/services/mtgjson/api.py
mightstone/services/mtgjson/commands.py
mightstone/services/mtgjson/models.py
mightstone/services/scryfall/__init__.py
mightstone/services/scryfall/api.py
mightstone/services/scryfall/commands.py
mightstone/services/scryfall/models.py
mightstone/services/scryfall/query.py
mightstone/services/wiki/__init__.py
mightstone/services/wiki/api.py
mightstone/services/wiki/commands.py
mightstone/services/wiki/models.py
mightstone-0.12.0.dist-info/LICENSE
mightstone-0.12.0.dist-info/METADATA
mightstone-0.12.0.dist-info/WHEEL
mightstone-0.12.0.dist-info/entry_points.txt
mightstone-0.12.0.dist-info/RECORD
