Metadata-Version: 2.1
Name: mightstone
Version: 0.12.0
Summary: A library manage all things Magic The Gathering related in python
Home-page: https://github.com/guibod/mightstone
License: MIT
Author: Guillaume Boddaert
Requires-Python: >=3.9.0,<=3.12
Classifier: Development Status :: 3 - Alpha
Classifier: Environment :: Console
Classifier: Framework :: AsyncIO
Classifier: License :: OSI Approved :: MIT License
Classifier: Programming Language :: Python :: 3
Classifier: Programming Language :: Python :: 3.9
Classifier: Programming Language :: Python :: 3.10
Classifier: Programming Language :: Python :: 3.11
Classifier: Programming Language :: Python :: 3.12
Classifier: Topic :: Games/Entertainment :: Board Games
Classifier: Topic :: Software Development :: Libraries
Classifier: Typing :: Typed
Requires-Dist: aiofiles (>=23.2.1,<24.0.0)
Requires-Dist: appdirs (>=1.4.4,<2.0.0)
Requires-Dist: asyncclick (>=8.1.7.2,<9.0.0.0)
Requires-Dist: asyncstdlib (>=3.10.5,<4.0.0)
Requires-Dist: beanie (==1.26.0)
Requires-Dist: beautifulsoup4 (>=4.12.3,<5.0.0)
Requires-Dist: cairosvg (>=2.6.0,<3.0.0)
Requires-Dist: hishel (>=0.0.27,<0.0.28)
Requires-Dist: ijson (>=3.2.0.post0,<4.0.0)
Requires-Dist: injector (>=0.21.0,<0.22.0)
Requires-Dist: lxml (>=5.2.2,<6.0.0)
Requires-Dist: mongomock-motor (>=0.0.29,<0.0.30)
Requires-Dist: motor (>=3.1.1,<4.0.0)
Requires-Dist: ordered-set (>=4.1.0,<5.0.0)
Requires-Dist: pillow (>=9.4,<11.0)
Requires-Dist: pydantic (>=2.7.3)
Requires-Dist: pydantic-extra-types (>=2.7.0,<3.0.0)
Requires-Dist: pydantic-settings (>=2.2.1,<3.0.0)
Requires-Dist: pylint-pydantic (==0.3.2)
Requires-Dist: pymongo-inmemory (>=0.4.2,<0.5.0)
Requires-Dist: pyparsing (>=3.1.2,<4.0.0)
Requires-Dist: pytest (>=8.2.2,<9.0.0)
Requires-Dist: python-slugify (>=8.0.0,<9.0.0)
Requires-Dist: pyyaml (>=6.0.0,<7.0.0)
Requires-Dist: requests (>=2.28.2,<3.0.0)
Requires-Dist: ruff (>=0.4.7,<0.5.0)
Requires-Dist: universalasync (>=0.3.1.2,<0.4.0.0)
Project-URL: Bug Tracker, https://github.com/guibod/mightstone/issues
Project-URL: Documentation, https://github.com/guibod/mightstone/blob/master/README.md
Project-URL: Repository, https://github.com/guibod/mightstone
